omCmsMain
